bizstats_auth/__init__.py
bizstats_auth/config.py
bizstats_auth/models/__init__.py
bizstats_auth/models/enums.py
bizstats_auth/models/results.py
bizstats_auth/models/schemas.py
bizstats_auth/rbac/__init__.py
bizstats_auth/rbac/permissions.py
bizstats_auth/rbac/roles.py
bizstats_auth/security/__init__.py
bizstats_auth/security/jwt.py
bizstats_auth/security/password.py
bizstats_auth/tokens/__init__.py
bizstats_auth/tokens/api_key.py
bizstats_auth-0.1.0.dist-info/METADATA
bizstats_auth-0.1.0.dist-info/WHEEL
bizstats_auth-0.1.0.dist-info/RECORD
