Metadata-Version: 2.4
Name: bizstats-auth
Version: 0.1.0
Summary: Enterprise authentication with JWT, RBAC, and multi-tenant support for BizStats applications
Project-URL: Homepage, https://bizstats.ai
Project-URL: Documentation, https://docs.bizstats.ai/packages/auth
Project-URL: Repository, https://bitbucket.org/absolut-e/smart-mcp
Author-email: "BizStats.AI" <account@absolut-e.com>
License: Proprietary
Keywords: api-keys,authentication,jwt,multi-tenant,oauth2,rbac
Classifier: Development Status :: 4 - Beta
Classifier: Intended Audience :: Developers
Classifier: License :: Other/Proprietary License
Classifier: Operating System :: OS Independent
Classifier: Programming Language :: Python :: 3
Classifier: Programming Language :: Python :: 3.11
Classifier: Programming Language :: Python :: 3.12
Classifier: Programming Language :: Python :: 3.13
Classifier: Topic :: Security
Classifier: Topic :: Software Development :: Libraries :: Python Modules
Requires-Python: >=3.11
Requires-Dist: bcrypt>=4.0.0
Requires-Dist: pydantic-settings>=2.0.0
Requires-Dist: pydantic[email]>=2.0.0
Requires-Dist: python-jose[cryptography]>=3.3.0
Provides-Extra: dev
Requires-Dist: black>=24.0.0; extra == 'dev'
Requires-Dist: mypy>=1.8.0; extra == 'dev'
Requires-Dist: pytest-asyncio>=0.23.0; extra == 'dev'
Requires-Dist: pytest-cov>=4.1.0; extra == 'dev'
Requires-Dist: pytest>=8.0.0; extra == 'dev'
Requires-Dist: ruff>=0.1.0; extra == 'dev'
Provides-Extra: test
Requires-Dist: pytest-asyncio>=0.23.0; extra == 'test'
Requires-Dist: pytest-cov>=4.1.0; extra == 'test'
Requires-Dist: pytest-mock>=3.12.0; extra == 'test'
Requires-Dist: pytest>=8.0.0; extra == 'test'
